SeismicFoldDbGis/FoldDbGis.py
SeismicFoldDbGis/__init__.py
SeismicFoldDbGis/entity/Base.py
SeismicFoldDbGis/entity/Bin.py
SeismicFoldDbGis/entity/__init__.py
tests/__init__.py
tests/test_folddbgis.py
SeismicFoldDbGis-0.1.0.dist-info/LICENSE
SeismicFoldDbGis-0.1.0.dist-info/METADATA
SeismicFoldDbGis-0.1.0.dist-info/WHEEL
SeismicFoldDbGis-0.1.0.dist-info/top_level.txt
SeismicFoldDbGis-0.1.0.dist-info/RECORD
