Metadata-Version: 2.1
Name: SeismicFoldDbGis
Version: 0.1.0
Summary: Loads calculated fold from CSV file to GIS database
Home-page: https://github.com/mysiar/seismic-fold_db_gis-python-package
Author: Piotr Synowiec
Author-email: psynowiec@gmail.com
License: UNKNOWN
Platform: UNKNOWN
Classifier: Programming Language :: Python :: 3
Classifier: License :: OSI Approved :: MIT License
Classifier: Operating System :: OS Independent
Requires-Python: >=3.6
